{
  "main": {
    "id": "13b27522dc57c868",
    "type": "split",
    "children": [
      {
        "id": "7ef2f1bb7c2253cd",
        "type": "tabs",
        "children": [
          {
            "id": "0d063495bdebe316",
            "type": "leaf",
            "state": {
              "type": "markdown",
              "state": {
                "file": "RAG/RAG Evaluation.md",
                "mode": "source",
                "source": false
              },
              "icon": "lucide-file",
              "title": "RAG Evaluation"
            }
          }
        ]
      }
    ],
    "direction": "vertical"
  },
  "left": {
    "id": "2c5f5301f7e96e3a",
    "type": "split",
    "children": [
      {
        "id": "8b72f40933679e5c",
        "type": "tabs",
        "children": [
          {
            "id": "fd4d8ba0550b482d",
            "type": "leaf",
            "state": {
              "type": "file-explorer",
              "state": {
                "sortOrder": "alphabetical",
                "autoReveal": false
              },
              "icon": "lucide-folder-closed",
              "title": "Files"
            }
          },
          {
            "id": "e30863eebe4c7997",
            "type": "leaf",
            "state": {
              "type": "search",
              "state": {
                "query": "",
                "matchingCase": false,
                "explainSearch": false,
                "collapseAll": false,
                "extraContext": false,
                "sortOrder": "alphabetical"
              },
              "icon": "lucide-search",
              "title": "Search"
            }
          },
          {
            "id": "2ddeeb795f76a609",
            "type": "leaf",
            "state": {
              "type": "bookmarks",
              "state": {},
              "icon": "lucide-bookmark",
              "title": "Bookmarks"
            }
          }
        ]
      }
    ],
    "direction": "horizontal",
    "width": 514.5
  },
  "right": {
    "id": "8e516f90ff888bfb",
    "type": "split",
    "children": [
      {
        "id": "bb50f9b2c3f3a5df",
        "type": "tabs",
        "children": [
          {
            "id": "8131d41d0865dab4",
            "type": "leaf",
            "state": {
              "type": "backlink",
              "state": {
                "file": "RAG/RAG Evaluation.md",
                "collapseAll": false,
                "extraContext": false,
                "sortOrder": "alphabetical",
                "showSearch": false,
                "searchQuery": "",
                "backlinkCollapsed": false,
                "unlinkedCollapsed": true
              },
              "icon": "links-coming-in",
              "title": "Backlinks for RAG Evaluation"
            }
          },
          {
            "id": "6f389f78a4375745",
            "type": "leaf",
            "state": {
              "type": "outgoing-link",
              "state": {
                "file": "Untitled.md",
                "linksCollapsed": false,
                "unlinkedCollapsed": true
              },
              "icon": "links-going-out",
              "title": "Outgoing links from Untitled"
            }
          },
          {
            "id": "7eb3610060107dad",
            "type": "leaf",
            "state": {
              "type": "tag",
              "state": {
                "sortOrder": "frequency",
                "useHierarchy": true,
                "showSearch": false,
                "searchQuery": ""
              },
              "icon": "lucide-tags",
              "title": "Tags"
            }
          },
          {
            "id": "c07f10d3253dc28b",
            "type": "leaf",
            "state": {
              "type": "all-properties",
              "state": {
                "sortOrder": "frequency",
                "showSearch": false,
                "searchQuery": ""
              },
              "icon": "lucide-archive",
              "title": "All properties"
            }
          },
          {
            "id": "517da6d68ead269b",
            "type": "leaf",
            "state": {
              "type": "outline",
              "state": {
                "file": "Untitled.md",
                "followCursor": false,
                "showSearch": false,
                "searchQuery": ""
              },
              "icon": "lucide-list",
              "title": "Outline of Untitled"
            }
          }
        ]
      }
    ],
    "direction": "horizontal",
    "width": 200
  },
  "left-ribbon": {
    "hiddenItems": {
      "switcher:Open quick switcher": false,
      "graph:Open graph view": false,
      "canvas:Create new canvas": false,
      "daily-notes:Open today's daily note": false,
      "templates:Insert template": false,
      "command-palette:Open command palette": false,
      "bases:Create new base": false
    }
  },
  "active": "0d063495bdebe316",
  "lastOpenFiles": [
    "Master Thesis/Impl/indexing_throughput.json",
    "Master Thesis/Impl/rag_api/uploads/public/financial_report_q4_2023_669a847b5e534684ad0f4ada1dae500f.txt",
    "Master Thesis/Impl/rag_api/uploads/public/contract_001_90c005775e174c7b94e1135a67a84b31.txt",
    "Master Thesis/Impl/metrics/__pycache__/computational_cost.cpython-312.pyc",
    "RAG/GraphRAG query process.md",
    "Tags.md",
    "image.png",
    "ML/K-means.md",
    "ML/Evaluation Metric Selection.md",
    "ML/Broadcast.md",
    "Master Thesis/Замечания комиссии.md",
    "RAG/RAG Evaluation.md",
    "Master Thesis/tasks.md",
    "Master Thesis/Текст к презентации RAG.md",
    "Master Thesis/Impl/rag_api/test_requirements.txt",
    "Master Thesis/Текст к презентации RAG.md.tmp.47280.1772566460422",
    "Master Thesis/Текст к презентации RAG.md.tmp.47280.1772566446154",
    "Master Thesis/Impl/run_eval.py.tmp.30132.1772490733134",
    "Master Thesis/Impl/metrics/computational_cost.py",
    "Master Thesis/Diagrams.md",
    "Master Thesis/Встречи/2 Встреча с научруком после предзащиты.md",
    "Master Thesis/Questions.md",
    "Master Thesis/Impl/results/naive_rag.jsonl",
    "Master Thesis/Impl/retrievers/__pycache__/naive_rag.cpython-312.pyc",
    "Master Thesis/Impl/rag_api/README.md",
    "Master Thesis/Impl/results.md",
    "Master Thesis/Встречи/1 Переработка архитектуры.md",
    "Inference/Layer-wise Quantization.md",
    "Inference/GPTQ Algorithm.md",
    "Inference/FLOPs.md",
    "Ideas/Summary on entities.md",
    "Inference/Quantization Grid.md",
    "Inference/Quantization.md",
    "Inference/PTQ.md",
    "Inference/QAT.md",
    "Inference/Perplexity.md",
    "Inference/OBQ.md",
    "RAG/LightRAG Impl/lightrag/api/static/swagger-ui/favicon-32x32.png",
    "RAG/LightRAG Impl/lightrag/api/README.assets/image-20250323194750379.png",
    "RAG/LightRAG Impl/lightrag/api/README.assets/image-20250323122754387.png",
    "RAG/LightRAG Impl/lightrag/api/README.assets/image-20250323123011220.png",
    "RAG/LightRAG Impl/lightrag/api/README.assets/image-20250323122538997.png",
    "RAG/LightRAG Impl/lightrag_webui/public/logo.svg",
    "RAG/LightRAG Impl/lightrag_webui/public/favicon.png",
    "RAG/LightRAG Impl/README.assets/iShot_2025-03-23_12.40.08.png",
    "RAG/LightRAG Impl/README.assets/b2aaf634151b4706892693ffb43d9093.png",
    "Untitled.canvas"
  ]
}